{"_ts":[1498907342,1498951002,1498995088,1499038954],"_r":{"breakdown":{"html":{"bytes":[21345,21346,21346,21345],"requests":[1,1,1,1]},"js":{"bytes":[157760,157761,157760,157760],"requests":[5,5,5,5]},"css":{"bytes":[26548,26550,26550,26550],"requests":[2,2,2,2]},"image":{"bytes":[2534223,2534235,2534237,2534237],"requests":[17,17,17,17]},"flash":{"bytes":[0,0,0,0],"requests":[0,0,0,0]},"font":{"bytes":[228348,228349,228349,228349],"requests":[6,6,6,6]},"other":{"bytes":[12194276,12232050,12123331,12207162],"requests":[3,3,3,3]}},"date":[1498907342,1498951002,1498995088,1499038954],"domElements":[571,571,571,571],"domInteractive":[5348,2003,1782,1515],"firstPaint":[1259,1183,1332,736],"fullyLoaded":[28041,36359,29622,27677],"id":["170701_RQ_HQ0","170701_X0_1198","170702_KT_HKZ","170702_DT_107P"],"loadTime":[8388,6345,7419,6024],"render":[1799,1787,2081,1200],"SpeedIndex":[12824,11528,15821,12815],"TTFB":[391,577,309,179],"videoFrames":[[{"_i":"frame_0000.jpg","_t":0,"_vc":0},{"_i":"frame_0018.jpg","_t":1800,"_vc":1},{"_i":"frame_0065.jpg","_t":6500,"_vc":1},{"_i":"frame_0087.jpg","_t":8700,"_vc":6},{"_i":"frame_0099.jpg","_t":9900,"_vc":8},{"_i":"frame_0108.jpg","_t":10800,"_vc":8},{"_i":"frame_0110.jpg","_t":11000,"_vc":8},{"_i":"frame_0114.jpg","_t":11400,"_vc":91},{"_i":"frame_0116.jpg","_t":11600,"_vc":91},{"_i":"frame_0118.jpg","_t":11800,"_vc":91},{"_i":"frame_0120.jpg","_t":12000,"_vc":91},{"_i":"frame_0122.jpg","_t":12200,"_vc":91},{"_i":"frame_0126.jpg","_t":12600,"_vc":91},{"_i":"frame_0134.jpg","_t":13400,"_vc":91},{"_i":"frame_0144.jpg","_t":14400,"_vc":92},{"_i":"frame_0165.jpg","_t":16500,"_vc":90},{"_i":"frame_0168.jpg","_t":16800,"_vc":90},{"_i":"frame_0191.jpg","_t":19100,"_vc":94},{"_i":"frame_0196.jpg","_t":19600,"_vc":94},{"_i":"frame_0198.jpg","_t":19800,"_vc":94},{"_i":"frame_0203.jpg","_t":20300,"_vc":88},{"_i":"frame_0205.jpg","_t":20500,"_vc":88},{"_i":"frame_0207.jpg","_t":20700,"_vc":88},{"_i":"frame_0216.jpg","_t":21600,"_vc":88},{"_i":"frame_0242.jpg","_t":24200,"_vc":88},{"_i":"frame_0244.jpg","_t":24400,"_vc":88},{"_i":"frame_0261.jpg","_t":26100,"_vc":91},{"_i":"frame_0266.jpg","_t":26600,"_vc":92},{"_i":"frame_0267.jpg","_t":26700,"_vc":92},{"_i":"frame_0271.jpg","_t":27100,"_vc":91},{"_i":"frame_0272.jpg","_t":27200,"_vc":91},{"_i":"frame_0279.jpg","_t":27900,"_vc":91},{"_i":"frame_0280.jpg","_t":28000,"_vc":93},{"_i":"frame_0283.jpg","_t":28300,"_vc":96},{"_i":"frame_0284.jpg","_t":28400,"_vc":98},{"_i":"frame_0286.jpg","_t":28600,"_vc":98},{"_i":"frame_0288.jpg","_t":28800,"_vc":98},{"_i":"frame_0290.jpg","_t":29000,"_vc":98},{"_i":"frame_0291.jpg","_t":29100,"_vc":98},{"_i":"frame_0295.jpg","_t":29500,"_vc":99},{"_i":"frame_0297.jpg","_t":29700,"_vc":99},{"_i":"frame_0300.jpg","_t":30000,"_vc":99},{"_i":"frame_0301.jpg","_t":30100,"_vc":100},{"_i":"frame_0302.jpg","_t":30200,"_vc":100}],[{"_i":"frame_0000.jpg","_t":0,"_vc":0},{"_i":"frame_0018.jpg","_t":1800,"_vc":1},{"_i":"frame_0026.jpg","_t":2600,"_vc":1},{"_i":"frame_0061.jpg","_t":6100,"_vc":1},{"_i":"frame_0064.jpg","_t":6400,"_vc":6},{"_i":"frame_0073.jpg","_t":7300,"_vc":8},{"_i":"frame_0079.jpg","_t":7900,"_vc":9},{"_i":"frame_0082.jpg","_t":8200,"_vc":20},{"_i":"frame_0083.jpg","_t":8300,"_vc":52},{"_i":"frame_0085.jpg","_t":8500,"_vc":55},{"_i":"frame_0087.jpg","_t":8700,"_vc":55},{"_i":"frame_0088.jpg","_t":8800,"_vc":55},{"_i":"frame_0093.jpg","_t":9300,"_vc":54},{"_i":"frame_0097.jpg","_t":9700,"_vc":54},{"_i":"frame_0099.jpg","_t":9900,"_vc":54},{"_i":"frame_0104.jpg","_t":10400,"_vc":55},{"_i":"frame_0112.jpg","_t":11200,"_vc":68},{"_i":"frame_0116.jpg","_t":11600,"_vc":74},{"_i":"frame_0117.jpg","_t":11700,"_vc":93},{"_i":"frame_0119.jpg","_t":11900,"_vc":93},{"_i":"frame_0131.jpg","_t":13100,"_vc":93},{"_i":"frame_0135.jpg","_t":13500,"_vc":93},{"_i":"frame_0137.jpg","_t":13700,"_vc":98},{"_i":"frame_0138.jpg","_t":13800,"_vc":98},{"_i":"frame_0142.jpg","_t":14200,"_vc":98},{"_i":"frame_0144.jpg","_t":14400,"_vc":97},{"_i":"frame_0146.jpg","_t":14600,"_vc":98},{"_i":"frame_0185.jpg","_t":18500,"_vc":98},{"_i":"frame_0194.jpg","_t":19400,"_vc":99},{"_i":"frame_0197.jpg","_t":19700,"_vc":99},{"_i":"frame_0199.jpg","_t":19900,"_vc":92},{"_i":"frame_0201.jpg","_t":20100,"_vc":91},{"_i":"frame_0207.jpg","_t":20700,"_vc":91},{"_i":"frame_0208.jpg","_t":20800,"_vc":92},{"_i":"frame_0210.jpg","_t":21000,"_vc":92},{"_i":"frame_0213.jpg","_t":21300,"_vc":91},{"_i":"frame_0214.jpg","_t":21400,"_vc":91},{"_i":"frame_0223.jpg","_t":22300,"_vc":91},{"_i":"frame_0226.jpg","_t":22600,"_vc":92},{"_i":"frame_0233.jpg","_t":23300,"_vc":91},{"_i":"frame_0238.jpg","_t":23800,"_vc":90},{"_i":"frame_0239.jpg","_t":23900,"_vc":90},{"_i":"frame_0240.jpg","_t":24000,"_vc":90},{"_i":"frame_0245.jpg","_t":24500,"_vc":90},{"_i":"frame_0248.jpg","_t":24800,"_vc":91},{"_i":"frame_0252.jpg","_t":25200,"_vc":90},{"_i":"frame_0254.jpg","_t":25400,"_vc":90},{"_i":"frame_0261.jpg","_t":26100,"_vc":90},{"_i":"frame_0265.jpg","_t":26500,"_vc":91},{"_i":"frame_0266.jpg","_t":26600,"_vc":92},{"_i":"frame_0271.jpg","_t":27100,"_vc":94},{"_i":"frame_0276.jpg","_t":27600,"_vc":94},{"_i":"frame_0278.jpg","_t":27800,"_vc":93},{"_i":"frame_0283.jpg","_t":28300,"_vc":91},{"_i":"frame_0290.jpg","_t":29000,"_vc":91},{"_i":"frame_0292.jpg","_t":29200,"_vc":90},{"_i":"frame_0294.jpg","_t":29400,"_vc":90},{"_i":"frame_0318.jpg","_t":31800,"_vc":89},{"_i":"frame_0324.jpg","_t":32400,"_vc":90},{"_i":"frame_0329.jpg","_t":32900,"_vc":89},{"_i":"frame_0335.jpg","_t":33500,"_vc":89},{"_i":"frame_0340.jpg","_t":34000,"_vc":89},{"_i":"frame_0345.jpg","_t":34500,"_vc":89},{"_i":"frame_0357.jpg","_t":35700,"_vc":88},{"_i":"frame_0362.jpg","_t":36200,"_vc":88},{"_i":"frame_0368.jpg","_t":36800,"_vc":88},{"_i":"frame_0373.jpg","_t":37300,"_vc":100},{"_i":"frame_0378.jpg","_t":37800,"_vc":100},{"_i":"frame_0383.jpg","_t":38300,"_vc":100}],[{"_i":"frame_0000.jpg","_t":0,"_vc":0},{"_i":"frame_0021.jpg","_t":2100,"_vc":1},{"_i":"frame_0024.jpg","_t":2400,"_vc":1},{"_i":"frame_0052.jpg","_t":5200,"_vc":6},{"_i":"frame_0061.jpg","_t":6100,"_vc":6},{"_i":"frame_0094.jpg","_t":9400,"_vc":8},{"_i":"frame_0112.jpg","_t":11200,"_vc":8},{"_i":"frame_0126.jpg","_t":12600,"_vc":8},{"_i":"frame_0130.jpg","_t":13000,"_vc":24},{"_i":"frame_0161.jpg","_t":16100,"_vc":26},{"_i":"frame_0165.jpg","_t":16500,"_vc":26},{"_i":"frame_0167.jpg","_t":16700,"_vc":26},{"_i":"frame_0175.jpg","_t":17500,"_vc":100},{"_i":"frame_0202.jpg","_t":20200,"_vc":100},{"_i":"frame_0213.jpg","_t":21300,"_vc":100},{"_i":"frame_0218.jpg","_t":21800,"_vc":100}],[{"_i":"frame_0000.jpg","_t":0,"_vc":0},{"_i":"frame_0012.jpg","_t":1200,"_vc":1},{"_i":"frame_0017.jpg","_t":1700,"_vc":1},{"_i":"frame_0062.jpg","_t":6200,"_vc":6},{"_i":"frame_0064.jpg","_t":6400,"_vc":8},{"_i":"frame_0067.jpg","_t":6700,"_vc":8},{"_i":"frame_0069.jpg","_t":6900,"_vc":8},{"_i":"frame_0071.jpg","_t":7100,"_vc":8},{"_i":"frame_0072.jpg","_t":7200,"_vc":11},{"_i":"frame_0076.jpg","_t":7600,"_vc":26},{"_i":"frame_0086.jpg","_t":8600,"_vc":47},{"_i":"frame_0098.jpg","_t":9800,"_vc":46},{"_i":"frame_0105.jpg","_t":10500,"_vc":47},{"_i":"frame_0107.jpg","_t":10700,"_vc":50},{"_i":"frame_0128.jpg","_t":12800,"_vc":49},{"_i":"frame_0131.jpg","_t":13100,"_vc":52},{"_i":"frame_0148.jpg","_t":14800,"_vc":54},{"_i":"frame_0150.jpg","_t":15000,"_vc":84},{"_i":"frame_0154.jpg","_t":15400,"_vc":84},{"_i":"frame_0156.jpg","_t":15600,"_vc":89},{"_i":"frame_0160.jpg","_t":16000,"_vc":89},{"_i":"frame_0165.jpg","_t":16500,"_vc":89},{"_i":"frame_0166.jpg","_t":16600,"_vc":89},{"_i":"frame_0173.jpg","_t":17300,"_vc":94},{"_i":"frame_0178.jpg","_t":17800,"_vc":94},{"_i":"frame_0179.jpg","_t":17900,"_vc":94},{"_i":"frame_0183.jpg","_t":18300,"_vc":94},{"_i":"frame_0188.jpg","_t":18800,"_vc":94},{"_i":"frame_0189.jpg","_t":18900,"_vc":94},{"_i":"frame_0197.jpg","_t":19700,"_vc":94},{"_i":"frame_0199.jpg","_t":19900,"_vc":94},{"_i":"frame_0202.jpg","_t":20200,"_vc":90},{"_i":"frame_0207.jpg","_t":20700,"_vc":89},{"_i":"frame_0210.jpg","_t":21000,"_vc":89},{"_i":"frame_0213.jpg","_t":21300,"_vc":88},{"_i":"frame_0221.jpg","_t":22100,"_vc":88},{"_i":"frame_0224.jpg","_t":22400,"_vc":89},{"_i":"frame_0226.jpg","_t":22600,"_vc":88},{"_i":"frame_0232.jpg","_t":23200,"_vc":88},{"_i":"frame_0233.jpg","_t":23300,"_vc":89},{"_i":"frame_0243.jpg","_t":24300,"_vc":94},{"_i":"frame_0252.jpg","_t":25200,"_vc":92},{"_i":"frame_0254.jpg","_t":25400,"_vc":92},{"_i":"frame_0255.jpg","_t":25500,"_vc":91},{"_i":"frame_0261.jpg","_t":26100,"_vc":91},{"_i":"frame_0262.jpg","_t":26200,"_vc":91},{"_i":"frame_0270.jpg","_t":27000,"_vc":91},{"_i":"frame_0273.jpg","_t":27300,"_vc":89},{"_i":"frame_0276.jpg","_t":27600,"_vc":89},{"_i":"frame_0277.jpg","_t":27700,"_vc":89},{"_i":"frame_0280.jpg","_t":28000,"_vc":89},{"_i":"frame_0282.jpg","_t":28200,"_vc":89},{"_i":"frame_0284.jpg","_t":28400,"_vc":89},{"_i":"frame_0286.jpg","_t":28600,"_vc":89},{"_i":"frame_0290.jpg","_t":29000,"_vc":89},{"_i":"frame_0292.jpg","_t":29200,"_vc":89},{"_i":"frame_0293.jpg","_t":29300,"_vc":89},{"_i":"frame_0296.jpg","_t":29600,"_vc":100}]],"visualComplete":[30100,37300,17500,29600],"lighthouse":[null,null,null,null],"pagespeed":[67,67,67,67]}}